aia.py
aia-0.2.0.dist-info/LICENSE.txt
aia-0.2.0.dist-info/METADATA
aia-0.2.0.dist-info/WHEEL
aia-0.2.0.dist-info/top_level.txt
aia-0.2.0.dist-info/RECORD
