Metadata-Version: 2.1
Name: aia
Version: 0.2.0
Summary: AIA chasing through OpenSSL for TLS certificate chain building and verifying
Home-page: https://github.com/danilobellini/aia
Author: Danilo de Jesus da Silva Bellini
Author-email: danilo.bellini@gmail.com
License: 2-clause BSD
Platform: UNKNOWN
Classifier: Development Status :: 2 - Pre-Alpha
Classifier: Environment :: Web Environment
Classifier: Intended Audience :: Developers
Classifier: Intended Audience :: System Administrators
Classifier: License :: OSI Approved :: BSD License
Classifier: Operating System :: OS Independent
Classifier: Programming Language :: Python :: 3
Classifier: Programming Language :: Python :: 3.6
Classifier: Programming Language :: Python :: 3.7
Classifier: Programming Language :: Python :: 3.8
Classifier: Programming Language :: Python :: 3.9
Classifier: Programming Language :: Python :: 3 :: Only
Classifier: Topic :: Internet :: WWW/HTTP
Classifier: Topic :: Security
Classifier: Topic :: Security :: Cryptography
Classifier: Topic :: System :: Networking
Requires-Python: >=3.6
License-File: LICENSE.txt
